envee/__init__.py
envee/envee.py
envee/py.typed
envee-0.2.0.dist-info/LICENSE
envee-0.2.0.dist-info/METADATA
envee-0.2.0.dist-info/WHEEL
envee-0.2.0.dist-info/top_level.txt
envee-0.2.0.dist-info/RECORD
