Metadata-Version: 2.1
Name: envee
Version: 0.2.0
Summary: Read variables from environment or files into dataclasses
Author-email: René Buffat <rene@ctechnology.io>
License: BSD 3-Clause License
Project-URL: Homepage, https://github.com/c-technology/envee
Keywords: env,environment variables,docker secrets,settings,.env,dotenv
Classifier: Development Status :: 3 - Alpha
Classifier: Operating System :: OS Independent
Classifier: License :: OSI Approved :: BSD License
Classifier: Programming Language :: Python :: 3.8
Classifier: Programming Language :: Python :: 3.9
Classifier: Programming Language :: Python :: 3.10
Classifier: Programming Language :: Python :: 3.11
Classifier: Programming Language :: Python :: 3.12
Requires-Python: >=3.8
License-File: LICENSE
Requires-Dist: typing-extensions >=4.1.1 ; python_version < "3.11"
